ghoshell_container-0.3.0.dist-info/METADATA
ghoshell_container-0.3.0.dist-info/WHEEL
ghoshell_container-0.3.0.dist-info/entry_points.txt
ghoshell_container-0.3.0.dist-info/licenses/LICENSE
ghoshell_container/__init__.py
ghoshell_container/abcd.py
ghoshell_container/containers.py
ghoshell_container/utils.py
ghoshell_container-0.3.0.dist-info/RECORD
