Metadata-Version: 2.1
Name: ghoshell-container
Version: 0.3.0
Summary: the ioc container useful for Interface oriented programming
Author-Email: thirdgerb <thirdgerb@gmail.com>
License: MIT
Project-URL: Homepage, https://github.com/GhostInShells/ghoshell-container
Project-URL: Repository, https://github.com/GhostInShells/ghoshell-container
Requires-Python: >=3.10
Requires-Dist: typing-extensions>=4.12.0
